wattrex_driver_db/__init__.py
wattrex_driver_db/__version__.py
wattrex_driver_db/context.py
wattrex_driver_db/drv_db_dao_base.py
wattrex_driver_db/drv_db_dao_cache.py
wattrex_driver_db/drv_db_dao_master.py
wattrex_driver_db/drv_db_dao_utils.py
wattrex_driver_db/drv_db_engine.py
wattrex_driver_db/drv_db_types.py
wattrex_driver_db-0.0.113.dist-info/LICENSE.txt
wattrex_driver_db-0.0.113.dist-info/METADATA
wattrex_driver_db-0.0.113.dist-info/WHEEL
wattrex_driver_db-0.0.113.dist-info/top_level.txt
wattrex_driver_db-0.0.113.dist-info/RECORD
